comp_use/__init__.py
comp_use-0.1.0.dist-info/METADATA
comp_use-0.1.0.dist-info/WHEEL
comp_use-0.1.0.dist-info/top_level.txt
comp_use-0.1.0.dist-info/RECORD
