Metadata-Version: 2.4
Name: comp-use
Version: 0.1.0
Summary: A placeholder package for comp-use
Home-page: https://github.com/placeholder/comp-use
Author: Xiangyi Li
Author-email: xiangyi@benchflow.ai
Classifier: Programming Language :: Python :: 3
Classifier: License :: OSI Approved :: MIT License
Classifier: Operating System :: OS Independent
Requires-Python: >=3.6
Dynamic: author
Dynamic: author-email
Dynamic: classifier
Dynamic: description
Dynamic: description-content-type
Dynamic: home-page
Dynamic: requires-python
Dynamic: summary
